<timetable station="Berlin Heidelberger Platz" eva="8089112">

<s id="8122123837948517104-2605261358-8" eva="8089112">
    <ar ct="2605261413" l="S42"/>
    <dp ct="2605261413" l="S42"/>
</s>


<s id="4284279576656683442-2605261328-21" eva="8089112">
    <ar ct="2605261413" l="S41"/>
    <dp ct="2605261413" l="S41"/>
</s>


<s id="5237820512542372884-2605261428-8" eva="8089112">
    <ar ct="2605261442" l="S42"/>
    <dp ct="2605261443" l="S42"/>
</s>


<s id="-1922802170105418819-2605261428-21" eva="8089112">
    <ar ct="2605261512" l="S41"/>
    <dp ct="2605261513" l="S41"/>
</s>


<s id="6161033674559587323-2605261338-21" eva="8089112">
    <ar ct="2605261423" l="S41"/>
    <dp ct="2605261424" l="S41"/>
</s>


<s id="-4206069100090636820-2605261321-18" eva="8089112">
    <ar ct="2605261410" l="S46"/>
    <dp ct="2605261411" l="S46"/>
</s>


<s id="-8779951230096627311-2605261353-8" eva="8089112">
    <ar ct="2605261408" l="S42"/>
    <dp ct="2605261408" l="S42"/>
</s>


<s id="-3059387049798295218-2605261400-5" eva="8089112">
    <ar ct="2605261407" l="S41"/>
    <dp ct="2605261408" l="S41"/>
</s>


<s id="7779777142953412043-2605261423-8" eva="8089112">
    <ar ct="2605261437" l="S42"/>
    <dp ct="2605261438" l="S42"/>
</s>


<s id="7506856953739380250-2605261423-21" eva="8089112">
    <ar ct="2605261507" l="S41"/>
    <dp ct="2605261508" l="S41"/>
</s>


<s id="7809989061840363622-2605261356-6" eva="8089112">
    <ar ct="2605261405" l="S46"/>
    <dp ct="2605261406" l="S46"/>
</s>


<s id="-6236794398520287983-2605261333-21" eva="8089112">
    <ar ct="2605261418" l="S41"/>
    <dp ct="2605261419" l="S41"/>
</s>


<s id="-5430480272715375598-2605261421-18" eva="8089112">
    <ar ct="2605261510" l="S46"/>
    <dp ct="2605261510" l="S46"/>
</s>


<s id="2062805381225481990-2605261341-18" eva="8089112">
    <ar ct="2605261431" l="S46"/>
    <dp ct="2605261432" l="S46"/>
</s>


<s id="-3312176026804194316-2605261348-8" eva="8089112">
    <ar ct="2605261403" l="S42"/>
    <dp ct="2605261404" l="S42"/>
</s>


<s id="5272364581160869514-2605261318-21" eva="8089112">
    <ar ct="2605261402" l="S41"/>
    <dp ct="2605261403" l="S41"/>
</s>


<s id="6315881562382231720-2605261418-21" eva="8089112">
    <ar ct="2605261502" l="S41"/>
    <dp ct="2605261503" l="S41"/>
</s>


<s id="-8092723936177548765-2605261418-8" eva="8089112">
    <ar ct="2605261432" l="S42"/>
    <dp ct="2605261433" l="S42"/>
</s>


<s id="-7475383962454583885-2605261416-6" eva="8089112">
    <ar ct="2605261425" l="S46"/>
    <dp ct="2605261425" l="S46"/>
</s>


<s id="-2395578897901573417-2605261313-21" eva="8089112">
    <ar ct="2605261357" l="S41"/>
    <dp ct="2605261358" l="S41"/>
</s>


<s id="8733508633648754851-2605261413-8" eva="8089112">
    <ar ct="2605261427" l="S42"/>
    <dp ct="2605261428" l="S42"/>
</s>


<s id="-8278355018322708496-2605261413-21" eva="8089112">
    <ar ct="2605261457" l="S41"/>
    <dp ct="2605261458" l="S41"/>
</s>


<s id="8683156963302349940-2605261308-21" eva="8089112">
    <ar ct="2605261354" l="S41"/>
    <dp ct="2605261354" l="S41"/>
</s>


<s id="9130676215672728187-2605261338-8" eva="8089112">
    <ar ct="2605261353" l="S42"/>
    <dp ct="2605261354" l="S42"/>
</s>


<s id="3229055485746316100-2605261408-8" eva="8089112">
    <ar ct="2605261422" l="S42"/>
    <dp ct="2605261423" l="S42"/>
</s>


<s id="1077516802824487580-2605261408-21" eva="8089112">
    <ar ct="2605261452" l="S41"/>
    <dp ct="2605261453" l="S41"/>
</s>


<s id="-4474581227627402473-2605261301-18" eva="8089112">
    <ar ct="2605261351" l="S46"/>
    <dp ct="2605261352" l="S46"/>
</s>


<s id="4779777575731915929-2605261340-5" eva="8089112">
    <ar ct="2605261349" l="S41"/>
    <dp ct="2605261350" l="S41"/>
</s>


<s id="5548637658516435263-2605261333-8" eva="8089112">
    <ar ct="2605261347" l="S42"/>
    <dp ct="2605261348" l="S42"/>
</s>


<s id="4701659602580441425-2605261403-21" eva="8089112">
    <ar ct="2605261447" l="S41"/>
    <dp ct="2605261448" l="S41"/>
</s>


<s id="-396525327927466310-2605261403-8" eva="8089112">
    <ar ct="2605261417" l="S42"/>
    <dp ct="2605261418" l="S42"/>
</s>


<s id="8814852253708732052-2605261401-18" eva="8089112">
    <ar ct="2605261450" l="S46"/>
    <dp ct="2605261450" l="S46"/>
</s>


<s id="2597239673676875109-2605261336-6" eva="8089112">
    <ar ct="2605261345" l="S46"/>
    <dp ct="2605261345" l="S46"/>
</s>


<s id="2036791315146332181-2605261258-21" eva="8089112">
    <ar ct="2605261343" l="S41"/>
    <dp ct="2605261343" l="S41"/>
</s>


<s id="-3159030123589773645-2605261328-8" eva="8089112">
    <ar ct="2605261342" l="S42"/>
    <dp ct="2605261343" l="S42"/>
</s>


<s id="-7891420960927754941-2605261358-21" eva="8089112">
    <ar ct="2605261442" l="S41"/>
    <dp ct="2605261443" l="S41"/>
</s>


<s id="-3805824367521883224-2605261253-21" eva="8089112">
    <ar ct="2605261338" l="S41"/>
    <dp ct="2605261339" l="S41"/>
</s>


<s id="-7273078082454991151-2605261353-21" eva="8089112">
    <ar ct="2605261437" l="S41"/>
    <dp ct="2605261438" l="S41"/>
</s>


<s id="2463904654381575746-2605261248-21" eva="8089112">
    <ar ct="2605261333" l="S41"/>
    <dp ct="2605261333" l="S41"/>
</s>


<s id="-5823924435857972881-2605261318-8" eva="8089112">
    <ar ct="2605261333" l="S42"/>
    <dp ct="2605261333" l="S42"/>
</s>


<s id="8822339320363755158-2605261348-21" eva="8089112">
    <ar ct="2605261432" l="S41"/>
    <dp ct="2605261433" l="S41"/>
</s>


<s id="-7032752883441884847-2605261241-18" eva="8089112">
    <ar cpth="Königs Wusterhausen|Wildau|Zeuthen|Eichwalde|Berlin-Grünau|Berlin-Adlershof|Berlin-Johannisthal|Berlin-Schöneweide (S)|Berlin Baumschulenweg|Berlin Köllnische Heide|Berlin-Neukölln|Berlin Hermannstraße|Berlin-Tempelhof|Berlin Südkreuz (S)|Berlin-Schöneberg|Berlin Innsbrucker Platz|Berlin Bundesplatz" ct="2605261330" l="S46"/>
    <dp cpth="Berlin Hohenzollerndamm|Berlin-Halensee|Berlin Westkreuz|Berlin Messe Nord/ZOB (Witzleben)|Berlin Westend" ct="2605261331" l="S46"/>
</s>


<s id="2984154091469488919-2605261313-8" eva="8089112">
    <ar ct="2605261329" l="S42"/>
    <dp ct="2605261329" l="S42"/>
</s>


<s id="-1803750726826399355-2605261320-5" eva="8089112">
    <ar ct="2605261328" l="S41"/>
    <dp ct="2605261328" l="S41"/>
</s>


<s id="-5789558711774610642-2605261343-21" eva="8089112">
    <ar ct="2605261427" l="S41"/>
    <dp ct="2605261428" l="S41"/>
</s>


<s id="-8339743832550419349-2605261316-6" eva="8089112">
    <ar ct="2605261326" l="S46"/>
    <dp ct="2605261327" l="S46"/>
</s>


<s id="9077597139972168626-2605261238-21" eva="8089112">
    <ar ct="2605261323" l="S41"/>
    <dp ct="2605261324" l="S41"/>
</s>


<s id="6589685342604772047-2605261308-8" eva="8089112">
    <ar ct="2605261323" l="S42"/>
    <dp ct="2605261323" l="S42"/>
</s>


<s id="-3619681672281402569-2605261233-21" eva="8089112">
    <ar ct="2605261317" l="S41"/>
    <dp ct="2605261318" l="S41"/>
</s>


<s id="-8551443584374781516-2605261228-21" eva="8089112">
    <ar ct="2605261314" l="S41"/>
    <dp ct="2605261314" l="S41"/>
</s>


<s id="1974178392664028829-2605261258-8" eva="8089112">
    <ar ct="2605261313" l="S42"/>
    <dp ct="2605261313" l="S42"/>
</s>


<s id="-2164005168601296386-2605261221-18" eva="8089112">
    <ar cpth="Königs Wusterhausen|Wildau|Zeuthen|Eichwalde|Berlin-Grünau|Berlin-Adlershof|Berlin-Johannisthal|Berlin-Schöneweide (S)|Berlin Baumschulenweg|Berlin Köllnische Heide|Berlin-Neukölln|Berlin Hermannstraße|Berlin-Tempelhof|Berlin Südkreuz (S)|Berlin-Schöneberg|Berlin Innsbrucker Platz|Berlin Bundesplatz" ct="2605261310" l="S46"/>
    <dp cpth="Berlin Hohenzollerndamm|Berlin-Halensee|Berlin Westkreuz|Berlin Messe Nord/ZOB (Witzleben)|Berlin Westend" ct="2605261311" l="S46"/>
</s>


<s id="5531624195021303759-2605261253-8" eva="8089112">
    <ar ct="2605261308" l="S42"/>
    <dp ct="2605261308" l="S42"/>
</s>


<s id="-7322641168589316969-2605261256-6" eva="8089112">
    <ar ct="2605261306" l="S46"/>
    <dp ct="2605261306" l="S46"/>
</s>


<s id="5493611202689760529-2605261218-21" eva="8089112">
    <ar ct="2605261304" dc="1" l="S41"/>
    <dp ct="2605261305" l="S41"/>
</s>


<s id="-1817202928434414863-2605261248-8" eva="8089112">
    <ar ct="2605261302" l="S42"/>
    <dp ct="2605261303" l="S42"/>
</s>


<s id="-7677957203465953433-2605261213-21" eva="8089112">
    <ar ct="2605261258" l="S41"/>
    <dp ct="2605261258" l="S41"/>
</s>


<s id="3085297732873600569-2605261208-21" eva="8089112">
    <ar ct="2605261253" l="S41"/>
    <dp ct="2605261254" l="S41"/>
</s>


<s id="-1720900993681163785-2605261238-8" eva="8089112">
    <ar ct="2605261252" l="S42"/>
    <dp ct="2605261253" l="S42"/>
</s>


<s id="-6785924364462176401-2605261201-18" eva="8089112">
    <ar cpth="Wildau|Zeuthen|Eichwalde|Berlin-Grünau|Berlin-Adlershof|Berlin-Johannisthal|Berlin-Schöneweide (S)|Berlin Baumschulenweg|Berlin Köllnische Heide|Berlin-Neukölln|Berlin Hermannstraße|Berlin-Tempelhof|Berlin Südkreuz (S)|Berlin-Schöneberg|Berlin Innsbrucker Platz|Berlin Bundesplatz" ct="2605261250" l="S46"/>
    <dp cpth="Berlin Hohenzollerndamm|Berlin-Halensee|Berlin Westkreuz|Berlin Messe Nord/ZOB (Witzleben)|Berlin Westend" ct="2605261251" l="S46"/>
</s>


<s id="895330319088455769-2605261233-8" eva="8089112">
    <ar ct="2605261247" l="S42"/>
    <dp ct="2605261248" l="S42"/>
</s>


<s id="8053839109065869908-2605261158-21" eva="8089112">
    <ar ct="2605261246" l="S41"/>
    <dp ct="2605261246" l="S41"/>
</s>


<s id="3696614158348580612-2605261236-6" eva="8089112">
    <ar ct="2605261245" l="S46"/>
    <dp ct="2605261246" l="S46"/>
</s>


<s id="-2895826098464063538-2605261228-8" eva="8089112">
    <ar ct="2605261243" l="S42"/>
    <dp ct="2605261243" l="S42"/>
</s>


<s id="16439837419635188-2605261153-21" eva="8089112">
    <ar ct="2605261238" dc="1" l="S41"/>
    <dp ct="2605261238" l="S41"/>
</s>


<s id="4860914228797676152-2605261218-8" eva="8089112">
    <ar ct="2605261232" l="S42"/>
    <dp ct="2605261233" l="S42"/>
</s>


<s id="-8192139324405602477-2605261148-21" eva="8089112">
    <ar ct="2605261233" l="S41"/>
    <dp ct="2605261233" l="S41"/>
</s>


<s id="4154446247441422917-2605261141-18" eva="8089112">
    <ar cpth="Wildau|Zeuthen|Eichwalde|Berlin-Grünau|Berlin-Adlershof|Berlin-Johannisthal|Berlin-Schöneweide (S)|Berlin Baumschulenweg|Berlin Köllnische Heide|Berlin-Neukölln|Berlin Hermannstraße|Berlin-Tempelhof|Berlin Südkreuz (S)|Berlin-Schöneberg|Berlin Innsbrucker Platz|Berlin Bundesplatz" ct="2605261230" l="S46"/>
    <dp cpth="Berlin Hohenzollerndamm|Berlin-Halensee|Berlin Westkreuz|Berlin Messe Nord/ZOB (Witzleben)|Berlin Westend" ct="2605261230" l="S46"/>
</s>


<s id="7271114850422379294-2605261213-8" eva="8089112">
    <ar ct="2605261227" l="S42"/>
    <dp ct="2605261228" l="S42"/>
</s>


<s id="307297841266272814-2605261216-6" eva="8089112">
    <ar ct="2605261225" l="S46"/>
    <dp ct="2605261226" l="S46"/>
</s>


<s id="-2243113100543863371-2605261138-21" eva="8089112">
    <ar ct="2605261223" l="S41"/>
    <dp ct="2605261223" l="S41"/>
</s>


<s id="1050370327007109343-2605261208-8" eva="8089112">
    <ar ct="2605261222" l="S42"/>
    <dp ct="2605261223" l="S42"/>
</s>


<s id="926787398125017481-2605261133-21" eva="8089112">
    <ar ct="2605261218" l="S41"/>
    <dp ct="2605261218" l="S41"/>
</s>


<s id="-1650020202431664756-2605261128-21" eva="8089112">
    <ar ct="2605261213" l="S41"/>
    <dp ct="2605261214" l="S41"/>
</s>


<s id="343677701455122380-2605261158-8" eva="8089112">
    <ar ct="2605261212" l="S42"/>
    <dp ct="2605261213" l="S42"/>
</s>


<s id="2940518632189457885-2605261121-18" eva="8089112">
    <ar ct="2605261210" l="S46"/>
    <dp ct="2605261210" l="S46"/>
</s>


<s id="3849345755591750351-2605261153-8" eva="8089112">
    <ar ct="2605261207" l="S42"/>
    <dp ct="2605261208" l="S42"/>
</s>


<s id="-6881971447419261573-2605261156-6" eva="8089112">
    <ar ct="2605261205" l="S46"/>
    <dp ct="2605261206" l="S46"/>
</s>


<s id="4187099774503049118-2605261148-8" eva="8089112">
    <ar ct="2605261202" l="S42"/>
    <dp ct="2605261203" l="S42"/>
</s>


<s id="3316196534932478495-2605261118-21" eva="8089112">
    <ar ct="2605261203" cde="Berlin Südkreuz (S)" dc="1" l="S41"/>
    <dp ct="2605261203" l="S41"/>
</s>


<s id="-550967752426271128-2605261113-21" eva="8089112">
    <ar ct="2605261158" dc="1" l="S41"/>
    <dp ct="2605261158" l="S41"/>
</s>


<s id="8263754980513981064-2605261136-6" eva="8089112">
    <ar cpth="Berlin Westend|Berlin Messe Nord/ZOB (Witzleben)|Berlin Westkreuz|Berlin-Halensee|Berlin Hohenzollerndamm" ct="2605261146" l="S46"/>
    <dp cpth="Berlin Bundesplatz|Berlin Innsbrucker Platz|Berlin-Schöneberg|Berlin Südkreuz (S)|Berlin-Tempelhof|Berlin Hermannstraße|Berlin-Neukölln|Berlin Köllnische Heide|Berlin Baumschulenweg|Berlin-Schöneweide (S)|Berlin-Johannisthal|Berlin-Adlershof|Berlin-Grünau|Eichwalde|Zeuthen|Wildau|Königs Wusterhausen" ct="2605261147" l="S46"/>
</s>


<s id="-8879419934362369035-2605261116-6" eva="8089112">
    <ar cpth="Berlin Westend|Berlin Messe Nord/ZOB (Witzleben)|Berlin Westkreuz|Berlin-Halensee|Berlin Hohenzollerndamm" ct="2605261125" l="S46"/>
    <dp cpth="Berlin Bundesplatz|Berlin Innsbrucker Platz|Berlin-Schöneberg|Berlin Südkreuz (S)|Berlin-Tempelhof|Berlin Hermannstraße|Berlin-Neukölln|Berlin Köllnische Heide|Berlin Baumschulenweg|Berlin-Schöneweide (S)|Berlin-Johannisthal|Berlin-Adlershof|Berlin-Grünau|Eichwalde|Zeuthen|Wildau|Königs Wusterhausen" ct="2605261126" l="S46"/>
</s>


<s id="8692606127683523122-2605261108-21" eva="8089112">
    <ar ct="2605261153" l="S41"/>
    <dp ct="2605261153" l="S41"/>
</s>


<s id="7881239512109411365-2605261138-8" eva="8089112">
    <ar ct="2605261152" l="S42"/>
    <dp ct="2605261153" l="S42"/>
</s>


<s id="560601926045832134-2605261133-8" eva="8089112">
    <ar ct="2605261150" l="S42"/>
    <dp ct="2605261151" l="S42"/>
</s>


<s id="-1006337631067381777-2605261101-18" eva="8089112">
    <ar ct="2605261150" l="S46"/>
    <dp ct="2605261151" l="S46"/>
</s>


<s id="1673787176617985099-2605261056-6" eva="8089112">
    <ar cpth="Berlin Westend|Berlin Messe Nord/ZOB (Witzleben)|Berlin Westkreuz|Berlin-Halensee|Berlin Hohenzollerndamm" ct="2605261106" l="S46"/>
    <dp cpth="Berlin Bundesplatz|Berlin Innsbrucker Platz|Berlin-Schöneberg|Berlin Südkreuz (S)|Berlin-Tempelhof|Berlin Hermannstraße|Berlin-Neukölln|Berlin Köllnische Heide|Berlin Baumschulenweg|Berlin-Schöneweide (S)|Berlin-Johannisthal|Berlin-Adlershof|Berlin-Grünau|Eichwalde|Zeuthen|Wildau" ct="2605261107" l="S46"/>
</s>


<s id="-8222793819201001095-2605261128-8" eva="8089112">
    <ar ct="2605261143" l="S42"/>
    <dp ct="2605261143" l="S42"/>
</s>


<s id="3306822541086914907-2605261058-21" eva="8089112">
    <ar ct="2605261143" l="S41"/>
    <dp ct="2605261143" l="S41"/>
</s>


<s id="-754645722021945419-2605261053-21" eva="8089112">
    <ar ct="2605261138" cde="Berlin Südkreuz (S)" dc="1" l="S41"/>
    <dp ct="2605261138" l="S41"/>
</s>


<s id="2334084281565051514-2605261036-6" eva="8089112">
    <ar cpth="Berlin Westend|Berlin Messe Nord/ZOB (Witzleben)|Berlin Westkreuz|Berlin-Halensee|Berlin Hohenzollerndamm" ct="2605261045" l="S46"/>
    <dp cpth="Berlin Bundesplatz|Berlin Innsbrucker Platz|Berlin-Schöneberg|Berlin Südkreuz (S)|Berlin-Tempelhof|Berlin Hermannstraße|Berlin-Neukölln|Berlin Köllnische Heide|Berlin Baumschulenweg|Berlin-Schöneweide (S)|Berlin-Johannisthal|Berlin-Adlershof|Berlin-Grünau|Eichwalde|Zeuthen|Wildau" ct="2605261046" l="S46"/>
</s>


<s id="6889826280459701291-2605261048-21" eva="8089112">
    <ar ct="2605261133" l="S41"/>
    <dp ct="2605261133" l="S41"/>
</s>


<s id="-5196830993051824139-2605261118-8" eva="8089112">
    <ar ct="2605261132" l="S42"/>
    <dp ct="2605261133" l="S42"/>
</s>


<s id="5817496419241698238-2605261041-18" eva="8089112">
    <ar ct="2605261130" l="S46"/>
    <dp ct="2605261131" l="S46"/>
</s>


<s id="-2195145722643483148-2605261113-8" eva="8089112">
    <ar ct="2605261127" l="S42"/>
    <dp ct="2605261128" l="S42"/>
</s>


<s id="-1790332421146665029-2605261038-21" eva="8089112">
    <ar ct="2605261124" l="S41"/>
    <dp ct="2605261124" l="S41"/>
</s>


<s id="-6374104091925868885-2605261108-8" eva="8089112">
    <ar ct="2605261122" l="S42"/>
    <dp ct="2605261123" l="S42"/>
</s>


<s id="4768323470871052017-2605261033-21" eva="8089112">
    <ar ct="2605261118" l="S41"/>
    <dp ct="2605261119" l="S41"/>
</s>


<s id="-6633938139899615212-2605261028-21" eva="8089112">
    <ar ct="2605261116" l="S41"/>
    <dp ct="2605261117" l="S41"/>
</s>


<s id="6137287502367882296-2605261058-8" eva="8089112">
    <ar ct="2605261112" l="S42"/>
    <dp ct="2605261113" l="S42"/>
</s>


<s id="-6112341857996034516-2605261021-18" eva="8089112">
    <ar ct="2605261110" l="S46"/>
    <dp ct="2605261110" l="S46"/>
</s>


<s id="-3569709212774797835-2605261053-8" eva="8089112">
    <ar ct="2605261108" l="S42"/>
    <dp ct="2605261109" l="S42"/>
</s>


<s id="1868422363507140076-2605261048-8" eva="8089112">
    <ar ct="2605261102" l="S42"/>
    <dp ct="2605261103" l="S42"/>
</s>


<s id="-6300326682289718318-2605261018-21" eva="8089112">
    <ar cpth="Berlin Südkreuz (S)|Berlin-Schöneberg|Berlin Innsbrucker Platz|Berlin Bundesplatz" ct="2605261103" cs="p" clt="2605261028" l="S41"/>
    <dp cpth="Berlin Hohenzollerndamm|Berlin-Halensee|Berlin Westkreuz|Berlin Messe Nord/ZOB (Witzleben)|Berlin Westend|Berlin Jungfernheide (S)|Berlin Beusselstraße" ct="2605261103" cs="p" clt="2605261028" l="S41"/>
</s>


<s id="8425478567724610645-2605261013-21" eva="8089112">
    <ar ct="2605261058" dc="1" l="S41"/>
    <dp ct="2605261058" l="S41"/>
</s>


<s id="-1588768702219331514-2605261008-21" eva="8089112">
    <ar ct="2605261054" l="S41"/>
    <dp ct="2605261055" l="S41"/>
</s>


<s id="-3106454146193959631-2605261038-8" eva="8089112">
    <ar ct="2605261053" dc="1" l="S42"/>
    <dp ct="2605261054" l="S42"/>
</s>


<s id="4512856949740414772-2605261001-18" eva="8089112">
    <ar ct="2605261052" l="S46"/>
    <dp ct="2605261053" l="S46"/>
</s>


<s id="-3092144844610362951-2605261033-8" eva="8089112">
    <ar ct="2605261048" l="S42"/>
    <dp ct="2605261049" l="S42"/>
</s>


<s id="-7898075018113325225-2605260958-21" eva="8089112">
    <ar ct="2605261043" l="S41"/>
    <dp ct="2605261043" l="S41"/>
</s>


<s id="-3607581714967044358-2605261028-8" eva="8089112">
    <ar ct="2605261043" l="S42"/>
    <dp ct="2605261043" l="S42"/>
</s>


<s id="4322557676435895163-2605260818-21" eva="8089112">
    <ar ct="2605260904" l="S41"/>
    <dp ct="2605260905" dc="1" l="S41"/>
</s>


<s id="4093757469891861303-2605260918-21" eva="8089112">
    <ar ct="2605261011" l="S41"/>
    <dp ct="2605261012" dc="1" l="S41"/>
</s>


<s id="-6423325192722780972-2605261023-8" eva="8089112">
    <ar ct="2605261038" l="S42"/>
    <dp ct="2605261039" l="S42"/>
</s>


<s id="6869586188060584513-2605260953-21" eva="8089112">
    <ar cpth="Berlin Südkreuz (S)|Berlin-Schöneberg|Berlin Innsbrucker Platz|Berlin Bundesplatz" ct="2605261038" cs="p" clt="2605260958" l="S41"/>
    <dp cpth="Berlin Hohenzollerndamm|Berlin-Halensee|Berlin Westkreuz|Berlin Messe Nord/ZOB (Witzleben)|Berlin Westend|Berlin Jungfernheide (S)|Berlin Beusselstraße" ct="2605261038" cs="p" clt="2605260958" l="S41"/>
</s>


<s id="5867978840487226987-2605260948-21" eva="8089112">
    <ar ct="2605261032" l="S41"/>
    <dp ct="2605261033" l="S41"/>
</s>


<s id="-6356226425564007700-2605261018-8" eva="8089112">
    <ar ct="2605261032" l="S42"/>
    <dp ct="2605261033" l="S42"/>
</s>


<s id="5329830437275051929-2605260941-18" eva="8089112">
    <ar ct="2605261030" l="S46"/>
    <dp ct="2605261031" l="S46"/>
</s>


<s id="-6999363325648837318-2605261013-8" eva="8089112">
    <ar ct="2605261028" l="S42"/>
    <dp ct="2605261029" l="S42"/>
</s>


<s id="3836026739890168878-2605260943-21" eva="8089112">
    <ar ct="2605261028" l="S41"/>
    <dp ct="2605261028" l="S41"/>
</s>


<s id="3892721336257727309-2605261016-6" eva="8089112">
    <ar ct="2605261026" l="S46"/>
    <dp ct="2605261026" l="S46"/>
</s>


<s id="592969787362250928-2605260938-21" eva="8089112">
    <ar ct="2605261024" l="S41"/>
    <dp ct="2605261024" l="S41"/>
</s>


<s id="-588133005062669210-2605261008-8" eva="8089112">
    <ar ct="2605261022" l="S42"/>
    <dp ct="2605261023" l="S42"/>
</s>


<s id="-3066199810930166796-2605260933-21" eva="8089112">
    <ar ct="2605261019" l="S41"/>
    <dp ct="2605261020" l="S41"/>
</s>


<s id="-7293529809193731807-2605261003-8" eva="8089112">
    <ar ct="2605261017" l="S42"/>
    <dp ct="2605261018" l="S42"/>
</s>


<s id="-1301376445485440422-2605260928-21" eva="8089112">
    <ar ct="2605261017" l="S41"/>
    <dp ct="2605261018" l="S41"/>
</s>


<s id="7015051213231927625-2605260921-18" eva="8089112">
    <ar ct="2605261015" l="S46"/>
    <dp ct="2605261016" l="S46"/>
</s>


<s id="2796080378098646019-2605260923-21" eva="8089112">
    <ar ct="2605261013" l="S41"/>
    <dp ct="2605261014" l="S41"/>
</s>


<s id="-8979721155244129125-2605260958-8" eva="8089112">
    <ar ct="2605261012" l="S42"/>
    <dp ct="2605261013" l="S42"/>
</s>


<s id="4965911790015696872-2605260953-8" eva="8089112">
    <ar ct="2605261010" l="S42"/>
    <dp ct="2605261011" l="S42"/>
</s>


<s id="-2547344005021506872-2605260956-6" eva="8089112">
    <ar cpth="Berlin Hohenzollerndamm" ct="2605261008" l="S46"/>
    <dp cpth="Berlin Bundesplatz|Berlin Innsbrucker Platz|Berlin-Schöneberg|Berlin Südkreuz (S)|Berlin-Tempelhof|Berlin Hermannstraße|Berlin-Neukölln|Berlin Köllnische Heide|Berlin Baumschulenweg|Berlin-Schöneweide (S)|Berlin-Johannisthal|Berlin-Adlershof|Berlin-Grünau|Eichwalde|Zeuthen|Wildau|Königs Wusterhausen" ct="2605261009" l="S46"/>
</s>


<s id="-2695440956305972535-2605260753-21" eva="8089112">
    <ar ct="2605260838" l="S41"/>
    <dp ct="2605260838" dc="1" l="S41"/>
</s>


<s id="-4501948789885285652-2605260853-21" eva="8089112">
    <ar ct="2605260945" l="S41"/>
    <dp ct="2605260946" dc="1" l="S41"/>
</s>


<s id="5360343033178043446-2605260948-8" eva="8089112">
    <ar ct="2605261002" l="S42"/>
    <dp ct="2605261003" l="S42"/>
</s>


<s id="1873008746690375294-2605260943-8" eva="8089112">
    <ar ct="2605260958" l="S42"/>
    <dp ct="2605260958" l="S42"/>
</s>


<s id="-3422084149648064520-2605260901-18" eva="8089112">
    <ar cpth="Königs Wusterhausen|Wildau|Zeuthen|Eichwalde|Berlin-Grünau|Berlin-Adlershof|Berlin-Johannisthal|Berlin-Schöneweide (S)|Berlin Baumschulenweg|Berlin Köllnische Heide|Berlin-Neukölln|Berlin Hermannstraße|Berlin-Tempelhof|Berlin Südkreuz (S)|Berlin-Schöneberg|Berlin Innsbrucker Platz|Berlin Bundesplatz" ct="2605260956" cs="p" clt="2605260943" l="S46"/>
    <dp cpth="Berlin Hohenzollerndamm|Berlin-Halensee|Berlin Westkreuz|Berlin Messe Nord/ZOB (Witzleben)|Berlin Westend" ct="2605260956" cs="p" clt="2605260943" l="S46"/>
</s>


<s id="2678491364057526163-2605260908-21" eva="8089112">
    <ar ct="2605260953" l="S41"/>
    <dp ct="2605260953" l="S41"/>
</s>


<s id="-8213520851967673218-2605260938-8" eva="8089112">
    <ar ct="2605260953" dc="1" l="S42">
        <m id="r57761781" t="f" c="0" ts="2605260811" ts-tts="26-05-26 08:11:19.821"/>
        <m id="r57761782" t="f" c="0" ts="2605260811" ts-tts="26-05-26 08:11:19.821"/>
        <m id="r57761783" t="f" c="0" ts="2605260811" ts-tts="26-05-26 08:11:19.821"/>
        <m id="r57761784" t="f" c="0" ts="2605260811" ts-tts="26-05-26 08:11:19.821"/>
    </ar>
    <dp ct="2605260953" l="S42">
        <m id="r57761781" t="f" c="0" ts="2605260811" ts-tts="26-05-26 08:11:19.821"/>
        <m id="r57761782" t="f" c="0" ts="2605260811" ts-tts="26-05-26 08:11:19.821"/>
        <m id="r57761783" t="f" c="0" ts="2605260811" ts-tts="26-05-26 08:11:19.821"/>
        <m id="r57761784" t="f" c="0" ts="2605260811" ts-tts="26-05-26 08:11:19.821"/>
    </dp>
</s>


<s id="-9146331568353513137-2605260903-21" eva="8089112">
    <ar ct="2605260949" l="S41"/>
    <dp ct="2605260950" l="S41"/>
</s>


<s id="7274192366431737057-2605260933-8" eva="8089112">
    <ar ct="2605260948" l="S42"/>
    <dp ct="2605260948" l="S42"/>
</s>


<s id="-3094080370564111444-2605260858-21" eva="8089112">
    <ar ct="2605260947" l="S41"/>
    <dp ct="2605260948" l="S41"/>
</s>


<s id="-330452985828520485-2605260936-6" eva="8089112">
    <ar ct="2605260945" l="S46"/>
    <dp ct="2605260946" l="S46"/>
</s>


<s id="5177369266472112603-2605260841-18" eva="8089112">
    <ar cpth="Königs Wusterhausen|Wildau|Zeuthen|Eichwalde|Berlin-Grünau|Berlin-Adlershof|Berlin-Johannisthal|Berlin-Schöneweide (S)|Berlin Baumschulenweg|Berlin Köllnische Heide|Berlin-Neukölln|Berlin Hermannstraße|Berlin-Tempelhof|Berlin Südkreuz (S)|Berlin-Schöneberg|Berlin Innsbrucker Platz|Berlin Bundesplatz" ct="2605260943" l="S46"/>
    <dp cpth="Berlin Hohenzollerndamm|Berlin-Halensee|Berlin Charlottenburg (S)" ct="2605260944" l="S46"/>
</s>


<s id="-5607445359259728331-2605260713-21" eva="8089112">
    <ar ct="2605260758" l="S41"/>
    <dp ct="2605260758" dc="1" l="S41"/>
</s>


<s id="-536544038543590270-2605260813-21" eva="8089112">
    <ar ct="2605260858" l="S41"/>
    <dp ct="2605260858" cde="Berlin-Tempelhof" dc="1" l="S41"/>
</s>


<s id="1068552135197251628-2605260913-21" eva="8089112">
    <ar cpth="Berlin Beusselstraße|Berlin Westhafen|Berlin-Wedding|Berlin Gesundbrunnen(S)|Berlin Schönhauser Allee|Berlin Prenzlauer Allee|Berlin Greifswalder Str|Berlin Landsberger Allee|Berlin Storkower Str|Berlin Frankfurter Allee|Berlin Ostkreuz (S)|Berlin Treptower Park|Berlin Sonnenallee|Berlin-Neukölln|Berlin Hermannstraße|Berlin-Tempelhof" ct="2605260957" cs="c" clt="2605260945" l="S41"/>
    <dp cpth="" ct="2605260958" cs="c" clt="2605260945" l="S41"/>
</s>


<s id="-2541958349142976440-2605260928-8" eva="8089112">
    <ar ct="2605260942" l="S42"/>
    <dp ct="2605260943" l="S42"/>
</s>


<s id="-7359586879648500188-2605260923-8" eva="8089112">
    <ar ct="2605260937" l="S42"/>
    <dp ct="2605260938" l="S42"/>
</s>


<s id="38984504169811555-2605260848-21" eva="8089112">
    <ar ct="2605260933" l="S41"/>
    <dp ct="2605260933" l="S41"/>
</s>


<s id="-8203268392178314228-2605260918-8" eva="8089112">
    <ar ct="2605260932" l="S42"/>
    <dp ct="2605260933" l="S42"/>
</s>


<s id="4387684096000536409-2605260843-21" eva="8089112">
    <ar ct="2605260928" l="S41"/>
    <dp ct="2605260929" l="S41"/>
</s>


<s id="-2735335947138066193-2605260913-8" eva="8089112">
    <ar ct="2605260927" l="S42"/>
    <dp ct="2605260928" l="S42"/>
</s>


<s id="-5753026379310696589-2605260916-6" eva="8089112">
    <ar ct="2605260925" l="S46"/>
    <dp ct="2605260926" l="S46"/>
</s>


<s id="-6093571110288798450-2605260908-8" eva="8089112">
    <ar ct="2605260922" l="S42"/>
    <dp ct="2605260923" l="S42"/>
</s>


<s id="6353074317074160701-2605260838-21" eva="8089112">
    <ar ct="2605260923" l="S41"/>
    <dp ct="2605260923" l="S41"/>
</s>


<s id="5696088115119565621-2605260833-21" eva="8089112">
    <ar ct="2605260918" l="S41"/>
    <dp ct="2605260918" l="S41"/>
</s>


<s id="2305013733887078366-2605260903-8" eva="8089112">
    <ar ct="2605260917" l="S42"/>
    <dp ct="2605260918" l="S42"/>
</s>


<s id="-393169287984740832-2605260828-21" eva="8089112">
    <ar ct="2605260915" l="S41"/>
    <dp ct="2605260916" l="S41"/>
</s>


<s id="2895259994102907951-2605260858-8" eva="8089112">
    <ar ct="2605260912" l="S42"/>
    <dp ct="2605260913" l="S42"/>
</s>


<s id="2434982940497696784-2605260821-18" eva="8089112">
    <ar ct="2605260913" l="S46"/>
    <dp ct="2605260913" l="S46"/>
</s>


<s id="-1501200102612788739-2605260853-8" eva="8089112">
    <ar ct="2605260910" l="S42"/>
    <dp ct="2605260911" l="S42"/>
</s>


<s id="2286387872883253975-2605260823-21" eva="8089112">
    <ar ct="2605260908" l="S41"/>
    <dp ct="2605260908" l="S41"/>
</s>


<s id="3238393513524062564-2605260856-6" eva="8089112">
    <ar ct="2605260907" l="S46"/>
    <dp ct="2605260908" l="S46"/>
</s>


<s id="-8597249134610499180-2605260848-8" eva="8089112">
    <ar ct="2605260902" l="S42"/>
    <dp ct="2605260903" l="S42"/>
</s>


<s id="2174563987286365740-2605260843-8" eva="8089112">
    <ar ct="2605260858" l="S42"/>
    <dp ct="2605260859" l="S42"/>
</s>


<s id="-2806508315889445611-2605260808-21" eva="8089112">
    <ar ct="2605260854" l="S41"/>
    <dp ct="2605260855" l="S41"/>
</s>


<s id="-2751460866259938347-2605260838-8" eva="8089112">
    <ar cpth="Berlin Beusselstraße|Berlin Jungfernheide (S)|Berlin Westend|Berlin Messe Nord/ZOB (Witzleben)|Berlin Westkreuz|Berlin-Halensee|Berlin Hohenzollerndamm" ct="2605260853" l="S42"/>
    <dp cpth="Berlin Bundesplatz|Berlin Innsbrucker Platz|Berlin-Schöneberg|Berlin Südkreuz (S)|Berlin-Tempelhof|Berlin Hermannstraße|Berlin-Neukölln|Berlin Köllnische Heide|Berlin Baumschulenweg|Berlin-Schöneweide (S)|Berlin-Johannisthal|Berlin-Adlershof|Berlin-Grünau" ct="2605260853" l="S42"/>
</s>


<s id="-6806682247006037384-2605260801-18" eva="8089112">
    <ar ct="2605260852" l="S46"/>
    <dp ct="2605260853" l="S46"/>
</s>


<s id="-2114982784931969589-2605260803-21" eva="8089112">
    <ar ct="2605260848" l="S41"/>
    <dp ct="2605260848" l="S41"/>
</s>


<s id="5085491779237854921-2605260833-8" eva="8089112">
    <ar ct="2605260847" l="S42"/>
    <dp ct="2605260848" l="S42"/>
</s>


<s id="5978109634612999773-2605260836-6" eva="8089112">
    <ar ct="2605260845" l="S46"/>
    <dp ct="2605260846" l="S46"/>
</s>


<s id="-4045648113622445013-2605260758-21" eva="8089112">
    <ar ct="2605260844" l="S41"/>
    <dp ct="2605260845" l="S41"/>
</s>


<s id="2140175503612971534-2605260828-8" eva="8089112">
    <ar ct="2605260842" l="S42"/>
    <dp ct="2605260843" l="S42"/>
</s>


<s id="1227618017671504252-2605260823-8" eva="8089112">
    <ar ct="2605260837" l="S42"/>
    <dp ct="2605260838" l="S42"/>
</s>


<s id="4014608672682644431-2605260748-21" eva="8089112">
    <ar ct="2605260834" l="S41"/>
    <dp ct="2605260835" l="S41"/>
</s>


<s id="-4383691265358348637-2605260818-8" eva="8089112">
    <ar ct="2605260832" l="S42"/>
    <dp ct="2605260833" l="S42"/>
</s>


<s id="-3248950571659505588-2605260741-18" eva="8089112">
    <ar ct="2605260832" l="S46"/>
    <dp ct="2605260832" l="S46"/>
</s>


<s id="6099747721735551092-2605260743-21" eva="8089112">
    <ar ct="2605260827" l="S41"/>
    <dp ct="2605260828" l="S41"/>
</s>


<s id="-4016239033272319033-2605260813-8" eva="8089112">
    <ar ct="2605260828" l="S42"/>
    <dp ct="2605260828" l="S42"/>
</s>


<s id="429362203401189678-2605260816-6" eva="8089112">
    <ar ct="2605260825" l="S46"/>
    <dp ct="2605260826" l="S46"/>
</s>


<s id="-1160057803840118628-2605260738-21" eva="8089112">
    <ar ct="2605260823" l="S41"/>
    <dp ct="2605260824" l="S41"/>
</s>


<s id="2911904560907577677-2605260808-8" eva="8089112">
    <ar ct="2605260822" l="S42"/>
    <dp ct="2605260823" l="S42"/>
</s>


<s id="6481795853459375663-2605260803-8" eva="8089112">
    <ar ct="2605260817" l="S42"/>
    <dp ct="2605260818" l="S42"/>
</s>


<s id="3000960157804559006-2605260733-21" eva="8089112">
    <ar ct="2605260818" l="S41"/>
    <dp ct="2605260818" l="S41"/>
</s>


<s id="886488211225662463-2605260721-18" eva="8089112">
    <ar ct="2605260815" l="S46"/>
    <dp ct="2605260815" l="S46"/>
</s>


<s id="998045232377439105-2605260728-21" eva="8089112">
    <ar ct="2605260813" l="S41"/>
    <dp ct="2605260813" l="S41"/>
</s>


<s id="-63457652084688090-2605260758-8" eva="8089112">
    <ar ct="2605260813" l="S42"/>
    <dp ct="2605260813" l="S42"/>
</s>


<s id="-5685992453357247571-2605260723-21" eva="8089112">
    <ar ct="2605260808" l="S41"/>
    <dp ct="2605260808" l="S41"/>
</s>


<s id="-3152227233214291675-2605260753-8" eva="8089112">
    <ar ct="2605260807" l="S42"/>
    <dp ct="2605260808" l="S42"/>
</s>


<s id="375008021876401193-2605260638-8" eva="8089112">
    <ar ct="2605260652" l="S42"/>
    <dp ct="2605260653" dc="1" l="S42"/>
</s>


<s id="-7526868870447892953-2605260738-8" eva="8089112">
    <ar ct="2605260752" l="S42"/>
    <dp ct="2605260753" cde="Berlin-Grünau" dc="1" l="S42"/>
</s>


<s id="8513996349774318165-2605260756-6" eva="8089112">
    <ar ct="2605260805" l="S46"/>
    <dp ct="2605260806" l="S46"/>
</s>


<s id="4579977180027650739-2605260748-8" eva="8089112">
    <ar ct="2605260803" l="S42"/>
    <dp ct="2605260803" l="S42"/>
</s>


<s id="-8984336132092923740-2605260718-21" eva="8089112">
    <ar ct="2605260803" l="S41"/>
    <dp ct="2605260803" l="S41"/>
</s>


<s id="-8904353827105678579-2605260743-8" eva="8089112">
    <ar ct="2605260758" l="S42"/>
    <dp ct="2605260758" l="S42"/>
</s>


<s id="6038910343784222705-2605260708-21" eva="8089112">
    <ar ct="2605260753" l="S41"/>
    <dp ct="2605260753" l="S41"/>
</s>


<s id="-5509127326250118163-2605260701-18" eva="8089112">
    <ar ct="2605260750" l="S46"/>
    <dp ct="2605260750" l="S46"/>
</s>


<s id="-6779962338982159023-2605260703-21" eva="8089112">
    <ar ct="2605260748" l="S41"/>
    <dp ct="2605260748" l="S41"/>
</s>


<s id="-4426485833451441975-2605260733-8" eva="8089112">
    <ar ct="2605260748" l="S42"/>
    <dp ct="2605260748" l="S42"/>
</s>


<s id="3909321172287427276-2605260736-6" eva="8089112">
    <ar ct="2605260746" l="S46"/>
    <dp ct="2605260746" l="S46"/>
</s>


<s id="7473991259274748731-2605260658-21" eva="8089112">
    <ar ct="2605260743" l="S41"/>
    <dp ct="2605260743" l="S41"/>
</s>


<s id="496278233686736892-2605260728-8" eva="8089112">
    <ar ct="2605260743" l="S42"/>
    <dp ct="2605260743" l="S42"/>
</s>


<s id="1999970513453681912-2605260653-21" eva="8089112">
    <ar ct="2605260738" l="S41"/>
    <dp ct="2605260738" l="S41"/>
</s>


<s id="-2527746905858996443-2605260723-8" eva="8089112">
    <ar ct="2605260737" l="S42"/>
    <dp ct="2605260738" l="S42"/>
</s>


<s id="-3958617845669930516-2605260648-21" eva="8089112">
    <ar ct="2605260733" l="S41"/>
    <dp ct="2605260734" l="S41"/>
</s>


<s id="-8222421554350450262-2605260718-8" eva="8089112">
    <ar ct="2605260732" l="S42"/>
    <dp ct="2605260733" l="S42"/>
</s>


<s id="-5023438061491662060-2605260641-18" eva="8089112">
    <ar ct="2605260730" l="S46"/>
    <dp ct="2605260730" l="S46"/>
</s>


<s id="1365568335165220092-2605260713-8" eva="8089112">
    <ar ct="2605260727" l="S42"/>
    <dp ct="2605260728" l="S42"/>
</s>


<s id="-6070382121289400868-2605260643-21" eva="8089112">
    <ar ct="2605260727" l="S41"/>
    <dp ct="2605260728" l="S41"/>
</s>


<s id="688240241296336612-2605260716-6" eva="8089112">
    <ar ct="2605260725" l="S46"/>
    <dp ct="2605260726" l="S46"/>
</s>


<s id="6457481396548382167-2605260638-21" eva="8089112">
    <ar ct="2605260723" l="S41"/>
    <dp ct="2605260723" l="S41"/>
</s>


<s id="3253980344955793808-2605260708-8" eva="8089112">
    <ar ct="2605260722" l="S42"/>
    <dp ct="2605260723" l="S42"/>
</s>


<s id="1651931071947738116-2605260633-21" eva="8089112">
    <ar ct="2605260718" l="S41"/>
    <dp ct="2605260718" l="S41"/>
</s>


<s id="140949832557414535-2605260703-8" eva="8089112">
    <ar ct="2605260717" l="S42"/>
    <dp ct="2605260718" l="S42"/>
</s>


<s id="8821440915139406989-2605260628-21" eva="8089112">
    <ar ct="2605260713" l="S41"/>
    <dp ct="2605260713" l="S41"/>
</s>


<s id="-6073454969290882456-2605260658-8" eva="8089112">
    <ar ct="2605260712" l="S42"/>
    <dp ct="2605260713" l="S42"/>
</s>


<s id="8308771357486211638-2605260621-18" eva="8089112">
    <ar ct="2605260710" l="S46"/>
    <dp ct="2605260711" l="S46"/>
</s>


<s id="2086243976487052471-2605260653-8" eva="8089112">
    <ar ct="2605260708" l="S42"/>
    <dp ct="2605260709" l="S42"/>
</s>


<s id="456281368215786411-2605260623-21" eva="8089112">
    <ar ct="2605260708" l="S41"/>
    <dp ct="2605260708" l="S41"/>
</s>


<s id="5331943282137492161-2605260656-6" eva="8089112">
    <ar ct="2605260706" l="S46"/>
    <dp ct="2605260706" l="S46"/>
</s>


<s id="7945752130248629171-2605260648-8" eva="8089112">
    <ar ct="2605260702" l="S42"/>
    <dp ct="2605260703" l="S42"/>
</s>


<s id="-4670783219496744464-2605260618-21" eva="8089112">
    <ar ct="2605260703" l="S41"/>
    <dp ct="2605260703" l="S41"/>
</s>


<s id="-803103148805485561-2605260613-21" eva="8089112">
    <ar ct="2605260658" l="S41"/>
    <dp ct="2605260658" l="S41"/>
</s>


<s id="-4302765632843127807-2605260643-8" eva="8089112">
    <ar ct="2605260657" l="S42"/>
    <dp ct="2605260658" l="S42"/>
</s>


<s id="2104740110619819504-2605260608-21" eva="8089112">
    <ar ct="2605260653" l="S41"/>
    <dp ct="2605260653" l="S41"/>
</s>


<s id="7587215226763874000-2605260633-8" eva="8089112">
    <ar ct="2605260648" l="S42"/>
    <dp ct="2605260648" l="S42"/>
</s>


<s id="273014058126863917-2605260603-21" eva="8089112">
    <ar ct="2605260648" l="S41"/>
    <dp ct="2605260648" l="S41"/>
</s>


<s id="-1592498470175047385-2605260636-6" eva="8089112">
    <ar ct="2605260645" l="S46"/>
    <dp ct="2605260646" l="S46"/>
</s>


<s id="-3187168540075797692-2605260558-21" eva="8089112">
    <ar ct="2605260643" l="S41"/>
    <dp ct="2605260644" l="S41"/>
</s>


<s id="-4620955272830255767-2605260628-8" eva="8089112">
    <ar ct="2605260642" l="S42"/>
    <dp ct="2605260643" l="S42"/>
</s>


<s id="7779646383727268886-2605260623-8" eva="8089112">
    <ar ct="2605260637" l="S42"/>
    <dp ct="2605260638" l="S42"/>
</s>


<s id="688660120021271968-2605260553-21" eva="8089112">
    <ar ct="2605260637" l="S41"/>
    <dp ct="2605260638" l="S41"/>
</s>


<s id="8823110854083802744-2605260618-8" eva="8089112">
    <ar ct="2605260632" l="S42"/>
    <dp ct="2605260633" l="S42"/>
</s>


<s id="531473593874467722-2605260548-21" eva="8089112">
    <ar ct="2605260633" l="S41"/>
    <dp ct="2605260633" l="S41"/>
</s>


<s id="-4193175200667020593-2605260613-8" eva="8089112">
    <ar ct="2605260629" l="S42"/>
    <dp ct="2605260629" l="S42"/>
</s>


<s id="-5198872156698415801-2605260543-21" eva="8089112">
    <ar ct="2605260627" l="S41"/>
    <dp ct="2605260628" l="S41"/>
</s>


<s id="-1751380916810346170-2605260616-6" eva="8089112">
    <ar ct="2605260625" l="S46"/>
    <dp ct="2605260626" l="S46"/>
</s>


<s id="6263611158519933415-2605260608-8" eva="8089112">
    <ar ct="2605260623" l="S42"/>
    <dp ct="2605260623" l="S42"/>
</s>


<s id="2817964890652545357-2605260538-21" eva="8089112">
    <ar ct="2605260623" dc="1" l="S41"/>
    <dp ct="2605260623" l="S41"/>
</s>


<s id="-1206849490225134020-2605260603-8" eva="8089112">
    <ar ct="2605260618" l="S42"/>
    <dp ct="2605260619" l="S42"/>
</s>


<s id="-1098796271176625064-2605260533-21" eva="8089112">
    <ar ct="2605260618" l="S41"/>
    <dp ct="2605260618" l="S41"/>
</s>


<s id="-1833590842506692926-2605260558-8" eva="8089112">
    <ar ct="2605260613" l="S42"/>
    <dp ct="2605260614" l="S42"/>
</s>


<s id="-8847239909007976043-2605260528-21" eva="8089112">
    <ar ct="2605260613" l="S41"/>
    <dp ct="2605260613" l="S41"/>
</s>


<s id="-9030523163940174413-2605260553-8" eva="8089112">
    <ar ct="2605260611" l="S42"/>
    <dp ct="2605260611" l="S42"/>
</s>


<s id="-4216712497894617144-2605260523-21" eva="8089112">
    <ar ct="2605260608" l="S41"/>
    <dp ct="2605260608" l="S41"/>
</s>


<s id="7328331137075260257-2605260548-8" eva="8089112">
    <ar ct="2605260606" l="S42"/>
    <dp ct="2605260606" l="S42"/>
</s>


<s id="-3960478017107434154-2605260518-21" eva="8089112">
    <ar ct="2605260603" l="S41"/>
    <dp ct="2605260603" l="S41"/>
</s>


<s id="5749235883903314681-2605260543-8" eva="8089112">
    <ar ct="2605260557" l="S42"/>
    <dp ct="2605260558" l="S42"/>
</s>


<s id="3177603908051531313-2605260513-21" eva="8089112">
    <ar ct="2605260557" l="S41"/>
    <dp ct="2605260558" l="S41"/>
</s>


<s id="9161268306419759730-2605260508-21" eva="8089112">
    <ar ct="2605260553" l="S41"/>
    <dp ct="2605260554" l="S41"/>
</s>


<s id="5127324635550135987-2605260538-8" eva="8089112">
    <ar ct="2605260552" l="S42"/>
    <dp ct="2605260553" l="S42"/>
</s>


<s id="-3101982101697255522-2605260510-14" eva="8089112">
    <ar ct="2605260547" l="S41"/>
    <dp ct="2605260548" l="S41"/>
</s>


<s id="-2400547417649519020-2605260533-8" eva="8089112">
    <ar ct="2605260547" l="S42"/>
    <dp ct="2605260548" l="S42"/>
</s>


<s id="7074993223005237914-2605260528-8" eva="8089112">
    <ar ct="2605260542" l="S42"/>
    <dp ct="2605260543" l="S42"/>
</s>


<s id="6763968088707706427-2605260458-21" eva="8089112">
    <ar ct="2605260542" l="S41"/>
    <dp ct="2605260543" l="S41"/>
</s>


<s id="6794860434471554286-2605260530-5" eva="8089112">
    <ar ct="2605260537" l="S41"/>
    <dp ct="2605260538" l="S41"/>
</s>


<s id="8460437527538568371-2605260518-8" eva="8089112">
    <ar ct="2605260532" l="S42"/>
    <dp ct="2605260533" l="S42"/>
</s>


<s id="1310397377064609884-2605260448-21" eva="8089112">
    <ar ct="2605260532" l="S41"/>
    <dp ct="2605260533" l="S41"/>
</s>


<s id="-8279964610096883950-2605260450-14" eva="8089112">
    <ar ct="2605260528" l="S41"/>
    <dp ct="2605260528" l="S41"/>
</s>


<s id="-7616722225347814346-2605260438-21" eva="8089112">
    <ar ct="2605260524" dc="1" l="S41">
        <m id="r57746783" t="f" c="0" ts="2605260358" ts-tts="26-05-26 03:58:58.005"/>
        <m id="r57746784" t="f" c="0" ts="2605260358" ts-tts="26-05-26 03:58:58.005"/>
        <m id="r57746785" t="f" c="0" ts="2605260358" ts-tts="26-05-26 03:58:58.005"/>
        <m id="r57746786" t="f" c="0" ts="2605260358" ts-tts="26-05-26 03:58:58.005"/>
    </ar>
    <dp ct="2605260524" l="S41">
        <m id="r57746783" t="f" c="0" ts="2605260358" ts-tts="26-05-26 03:58:58.005"/>
        <m id="r57746784" t="f" c="0" ts="2605260358" ts-tts="26-05-26 03:58:58.005"/>
        <m id="r57746785" t="f" c="0" ts="2605260358" ts-tts="26-05-26 03:58:58.005"/>
        <m id="r57746786" t="f" c="0" ts="2605260358" ts-tts="26-05-26 03:58:58.005"/>
    </dp>
</s>


<s id="-9062942860843576281-2605260508-8" eva="8089112">
    <ar ct="2605260522" l="S42"/>
    <dp ct="2605260523" l="S42"/>
</s>


<s id="-6643355421947533389-2605260516-2" eva="8089112">
    <ar ct="2605260518" l="S41"/>
    <dp ct="2605260518" l="S41"/>
</s>


<s id="7769467436203601831-2605260458-8" eva="8089112">
    <ar ct="2605260512" l="S42"/>
    <dp ct="2605260513" l="S42"/>
</s>


<s id="-4317619809128022477-2605260428-21" eva="8089112">
    <ar ct="2605260513" l="S41"/>
    <dp ct="2605260513" l="S41"/>
</s>


<s id="2065847493242049548-2605260440-11" eva="8089112">
    <ar ct="2605260508" l="S41"/>
    <dp ct="2605260508" l="S41"/>
</s>


<s id="4955264545808928030-2605260418-21" eva="8089112">
    <ar ct="2605260503" l="S41"/>
    <dp ct="2605260503" l="S41"/>
</s>


<s id="-2098955970692831510-2605260448-8" eva="8089112">
    <ar ct="2605260502" l="S42"/>
    <dp ct="2605260503" l="S42"/>
</s>


<s id="221474536379961600-2605260438-8" eva="8089112">
    <ar ct="2605260452" l="S42"/>
    <dp ct="2605260453" l="S42"/>
</s>


<s id="-271694970610446295-2605260408-21" eva="8089112">
    <ar ct="2605260452" l="S41"/>
    <dp ct="2605260453" l="S41"/>
</s>


<s id="8719769342073995577-2605260405-18" eva="8089112">
    <ar ct="2605260443" l="S41"/>
    <dp ct="2605260443" l="S41"/>
</s>


<s id="-1111351431147838041-2605260428-8" eva="8089112">
    <ar ct="2605260442" l="S42"/>
    <dp ct="2605260443" l="S42"/>
</s>


<s id="-3898299205741032695-2605260418-8" eva="8089112">
    <ar ct="2605260432" l="S42"/>
    <dp ct="2605260433" l="S42"/>
</s>


<s id="-9054372128207350960-2605260401-15" eva="8089112">
    <ar ct="2605260432" l="S41"/>
    <dp ct="2605260433" l="S41"/>
</s>


<s id="3917803887105446684-2605260408-8" eva="8089112">
    <ar ct="2605260422" l="S42"/>
    <dp ct="2605260423" l="S42"/>
</s>


<s id="-1020397874048675729-2605260411-2" eva="8089112">
    <ar ct="2605260415" l="S41"/>
    <dp ct="2605260415" l="S41"/>
</s>


<s id="7197989823153879241-2605260358-8" eva="8089112">
    <ar ct="2605260412" l="S42"/>
    <dp ct="2605260413" l="S42"/>
</s>


<s id="4452597677740860356-2605260355-4" eva="8089112">
    <ar ct="2605260402" l="S42"/>
    <dp ct="2605260403" l="S42"/>
</s>


<s id="-5867842893510111922-2605260345-18" eva="8089112">
    <ar cpth="Berlin Gesundbrunnen(S)|Berlin Schönhauser Allee|Berlin Prenzlauer Allee" ct="2605260431" cs="c" clt="2605260401" l="S41">
        <m id="r57746732" t="f" c="0" ts="2605260358" ts-tts="26-05-26 03:58:12.134"/>
    </ar>
    <dp cpth="" ct="2605260431" cs="c" clt="2605260401" l="S41">
        <m id="r57746732" t="f" c="0" ts="2605260358" ts-tts="26-05-26 03:58:12.134"/>
    </dp>
</s>

</timetable>
